slickpy/__init__.py
slickpy/application.py
slickpy/comp.py
slickpy/cookie.py
slickpy/functional.py
slickpy/lifespan.py
slickpy/multipart.py
slickpy/py.typed
slickpy/request.py
slickpy/response.py
slickpy/router.py
slickpy/typing.py
slickpy/middleware/__init__.py
slickpy/middleware/routing.py
slickpy-0.4.6.dist-info/LICENSE
slickpy-0.4.6.dist-info/METADATA
slickpy-0.4.6.dist-info/WHEEL
slickpy-0.4.6.dist-info/top_level.txt
slickpy-0.4.6.dist-info/zip-safe
slickpy-0.4.6.dist-info/RECORD
